<?xml version="1.0" encoding="UTF-8" standalone="yes"?>
<adjectives>
    <adjective>
        <affirmative>い</affirmative>
        <affirmativePolite>いです</affirmativePolite>
        <negative>くない</negative>
        <negativePolite>くないです</negativePolite>
        <past>かった</past>
        <pastPolite>かったです</pastPolite>
        <negativePast>くなかった</negativePast>
        <negativePastPolite>くなかったです</negativePastPolite>
        <local>い　adjective</local>
        <furagana>い</furagana>
    </adjective>
    <adjective>
        <affirmative>だ</affirmative>
        <affirmativePolite>です</affirmativePolite>
        <negative>ではない・じゃない</negative>
        <negativePolite>ではありません・じゃありません</negativePolite>
        <past>だった</past>
        <pastPolite>でした</pastPolite>
        <negativePast>ではなかった・じゃなかった</negativePast>
        <negativePastPolite>ではありませんでした・じゃありませんでした</negativePastPolite>
        <local>な　adjective</local>
        <furagana>な</furagana>
    </adjective>
</adjectives>